iqadataset/__init__.py
iqadataset/dataset.py
iqadataset/dataset_pytorch.py
iqadataset/demo.py
iqadataset/demo_pytorch.py
iqadataset/load_dataset.py
iqadataset/csv/A57.txt
iqadataset/csv/AADB.txt
iqadataset/csv/AVA.txt
iqadataset/csv/BAPPS.txt
iqadataset/csv/BIQ2021.txt
iqadataset/csv/CID2013.txt
iqadataset/csv/CIDIQ_MOS100.txt
iqadataset/csv/CIDIQ_MOS50.txt
iqadataset/csv/CSIQ.txt
iqadataset/csv/FLIVE.txt
iqadataset/csv/GFIQA.txt
iqadataset/csv/KADID-10k.txt
iqadataset/csv/KonIQ-10k.txt
iqadataset/csv/LIVE.txt
iqadataset/csv/LIVE_Challenge.txt
iqadataset/csv/LIVE_MD.txt
iqadataset/csv/MDID2013.txt
iqadataset/csv/MDID2016.txt
iqadataset/csv/MDIVL.txt
iqadataset/csv/PDAP-HDDS.txt
iqadataset/csv/PIPAL.txt
iqadataset/csv/PIQ2023.txt
iqadataset/csv/PieAPP.txt
iqadataset/csv/SDIVL.txt
iqadataset/csv/SPAQ.txt
iqadataset/csv/TID2008.txt
iqadataset/csv/TID2013.txt
iqadataset/csv/Toyama.txt
iqadataset/csv/UHD-IQA.txt
iqadataset/csv/VCLFER.txt
iqadataset/csv/Waterloo_Exploration.txt
iqadataset-0.1.3.dist-info/LICENSE
iqadataset-0.1.3.dist-info/METADATA
iqadataset-0.1.3.dist-info/WHEEL
iqadataset-0.1.3.dist-info/top_level.txt
iqadataset-0.1.3.dist-info/RECORD
