Metadata-Version: 2.1
Name: iqadataset
Version: 0.1.3
Summary: A collection of Image Quality Assessment (IQA) datasets
Home-page: https://github.com/icbcbicc/IQA-Dataset
Author: Zhongling Wang
Author-email: zhongling.wang@uwaterloo.ca
Classifier: Development Status :: 3 - Alpha
Classifier: Intended Audience :: Science/Research
Classifier: License :: OSI Approved :: MIT License
Classifier: Programming Language :: Python :: 3
Classifier: Topic :: Scientific/Engineering :: Image Processing
Requires-Python: >=3.6
License-File: LICENSE
Requires-Dist: pandas
Requires-Dist: pillow
Requires-Dist: torch
Requires-Dist: torchvision
Requires-Dist: wget
